COPYING
LICENSE.MIT
LICENSE.md
README.md
setup.cfg
setup.py
pyandex_disk/__init__.py
pyandex_disk/client.py
pyandex_disk/errors.py
pyandex_disk/requester.py
pyandex_disk/utils.py
pyandex_disk.egg-info/PKG-INFO
pyandex_disk.egg-info/SOURCES.txt
pyandex_disk.egg-info/dependency_links.txt
pyandex_disk.egg-info/requires.txt
pyandex_disk.egg-info/top_level.txt