Metadata-Version: 2.1
Name: pyandex-disk
Version: 1.0.0a0
Summary: Python HTTP API wrapper for Yandex Disk.
Author: Mikhail Volkov, leestarb
Author-email: freylis2@gmail.com
Maintainer: leestarb
Classifier: Development Status :: 3 - Alpha
Classifier: Intended Audience :: Developers
Classifier: License :: OSI Approved :: MIT License
Classifier: Operating System :: OS Independent
Classifier: Programming Language :: Python :: Implementation
Classifier: Programming Language :: Python :: 3
Classifier: Topic :: Internet :: WWW/HTTP
Classifier: Topic :: Internet :: WWW/HTTP :: Dynamic Content
Classifier: Topic :: Software Development :: Libraries
Classifier: Topic :: Software Development :: Libraries :: Python Modules
Requires-Python: >=3.5
License-File: LICENSE.MIT
License-File: LICENSE.md
License-File: COPYING
